template_KCEvers/__init__.py
template_KCEvers/example/__init__.py
template_KCEvers/example/funcs.py
template_KCEvers/tutorial/__init__.py
template_KCEvers/tutorial/funcs.py
template_kcevers-0.0.5.dist-info/METADATA
template_kcevers-0.0.5.dist-info/WHEEL
template_kcevers-0.0.5.dist-info/licenses/LICENSE.txt
template_kcevers-0.0.5.dist-info/RECORD
