Metadata-Version: 2.1
Name: template_KCEvers
Version: 0.0.5
Summary: A small example package
Author-email: Kyra Caitlin Evers <kyra.c.evers@gmail.com>
License: Copyright (c) 2022 Kyra Evers
License-File: LICENSE.txt
Classifier: License :: OSI Approved :: MIT License
Classifier: Operating System :: OS Independent
Classifier: Programming Language :: Python :: 3
Requires-Python: >=3.7
Requires-Dist: numpy==1.21.6
Requires-Dist: pathlib==1.0.1
